volcano/core/__init__.py
volcano/core/__main__.py
volcano/core/connection.py
volcano/core/cvt.py
volcano/core/db.py
volcano/core/demo.xml
volcano/core/errors.py
volcano/core/expr.py
volcano/core/msg_parser.py
volcano/core/web.py
volcano/core/www/__init__.py
volcano/core/www/alarms.js
volcano/core/www/diag.html
volcano/core/www/diag.js
volcano/core/www/favicon.ico
volcano/core/www/green_tiger.js
volcano/core/www/index.html
volcano/core/www/index.js
volcano/core/www/navbar.js
volcano/core/www/the_time.js
volcano/core/www/ext/angular/angular.min.js
volcano/core/www/ext/angular/angular.min.js.map
volcano/core/www/ext/bootstrap3/css/bootstrap-theme.min.css
volcano/core/www/ext/bootstrap3/css/bootstrap-theme.min.css.map
volcano/core/www/ext/bootstrap3/css/bootstrap.min.css
volcano/core/www/ext/bootstrap3/css/bootstrap.min.css.map
volcano/core/www/ext/bootstrap3/fonts/glyphicons-halflings-regular.eot
volcano/core/www/ext/bootstrap3/fonts/glyphicons-halflings-regular.svg
volcano/core/www/ext/bootstrap3/fonts/glyphicons-halflings-regular.ttf
volcano/core/www/ext/bootstrap3/fonts/glyphicons-halflings-regular.woff
volcano/core/www/ext/bootstrap3/fonts/glyphicons-halflings-regular.woff2
volcano/core/www/ext/bootstrap3/js/bootstrap.min.js
volcano/core/www/ext/bootstrap3/js/npm.js
volcano/core/www/ext/jquery/jquery.js
volcano/lib/__init__.py
volcano/lib/bin.py
volcano/lib/log.py
volcano/lib/modbus.py
volcano/lib/named_parameters.py
volcano/lib/stddef.py
volcano/lib/stdint.py
volcano/lib/stdsvc.py
volcano/lib/stdsvcdef.py
volcano/lib/tstamp.py
volcano/lib/variant.py
volcano/lib/vector.py
volcano/lib/xml_reader.py
volcano/mbsrv/__init__.py
volcano/mbsrv/__main__.py
volcano/mbsrv/device.py
volcano/mbsrv/mb_rules.py
volcano/mbsrv/mb_server.py
volcano/mbsrv/mb_srv_protocol.py
volcano/poller/__init__.py
volcano/poller/__main__.py
volcano/poller/base_ctx.py
volcano/poller/base_dev.py
volcano/poller/base_prot.py
volcano/poller/build_cfg.py
volcano/poller/channel_base.py
volcano_x-0.0.5.dist-info/LICENSE
volcano_x-0.0.5.dist-info/METADATA
volcano_x-0.0.5.dist-info/WHEEL
volcano_x-0.0.5.dist-info/top_level.txt
volcano_x-0.0.5.dist-info/RECORD
