Metadata-Version: 2.1
Name: volcano-x
Version: 0.0.5
Summary: VolcanoX on Python
Home-page: UNKNOWN
Author: Vinogradov D
Author-email: dgrapes@gmail.com
License: MIT
Platform: UNKNOWN
Classifier: Programming Language :: Python :: 3
Classifier: License :: OSI Approved :: MIT License
Classifier: Operating System :: OS Independent
Requires-Dist: twisted
Requires-Dist: pyserial
